setup.py
msg/__init__.py
msg/revMsg.py
msg/sendMsg.py
xuyangcao.egg-info/PKG-INFO
xuyangcao.egg-info/SOURCES.txt
xuyangcao.egg-info/dependency_links.txt
xuyangcao.egg-info/top_level.txt