Metadata-Version: 2.1
Name: xuyangcao
Version: 1.0
Summary: xuyangcao's model
Author: xuyangcao
